dynamicalsystem/halogen/__init__.py
dynamicalsystem/halogen/__main__.py
dynamicalsystem/halogen/config.py
dynamicalsystem/halogen/logging.py
dynamicalsystem/halogen/py.typed
dynamicalsystem/halogen/utils.py
dynamicalsystem_halogen-0.1.3.dist-info/METADATA
dynamicalsystem_halogen-0.1.3.dist-info/WHEEL
dynamicalsystem_halogen-0.1.3.dist-info/entry_points.txt
dynamicalsystem_halogen-0.1.3.dist-info/RECORD
