Metadata-Version: 2.4
Name: dynamicalsystem.halogen
Version: 0.1.3
Summary: Shared library from dynamicalsystem
Author: Simon Horrobin
Classifier: Development Status :: 3 - Alpha
Classifier: Intended Audience :: Developers
Classifier: License :: OSI Approved :: MIT License
Classifier: Topic :: Software Development :: Libraries :: Python Modules
Requires-Python: >=3.13
Requires-Dist: python-dotenv>=1.0.1
Requires-Dist: requests>=2.32.3
